LICENSE.txt
MANIFEST.in
README.md
SupplyChainAnalysis.py
pyproject.toml
setup.cfg
setup.py
SupplyChainAnalysis.egg-info/PKG-INFO
SupplyChainAnalysis.egg-info/SOURCES.txt
SupplyChainAnalysis.egg-info/dependency_links.txt
SupplyChainAnalysis.egg-info/entry_points.txt
SupplyChainAnalysis.egg-info/top_level.txt